{
  "data": [
    {
      "question": "question1",
      "options": [
        {
          "answer": "answer1-a",
          "type": { "J": 1 }
        },
        {
          "answer": "answer1-b",
          "type": { "J": -1 }
        }
      ]
    },
    {
      "question": "question2",
      "options": [
        {
          "answer": "answer2-a",
          "type": { "T": 1 }
        },
        {
          "answer": "answer2-b",
          "type": { "T": -1 }
        }
      ]
    },
    {
      "question": "question3",
      "options": [
        {
          "answer": "answer3-a",
          "type": { "J": 1 }
        },
        {
          "answer": "answer3-b",
          "type": { "J": -1 }
        }
      ]
    },
    {
      "question": "question4",
      "options": [
        {
          "answer": "answer4-a",
          "type": { "N": -1 }
        },
        {
          "answer": "answer4-b",
          "type": { "N": 1 }
        }
      ]
    },
    {
      "question": "question5",
      "options": [
        {
          "answer": "answer5-a",
          "type": { "N": 1 }
        },
        {
          "answer": "answer5-b",
          "type": { "N": -1 }
        }
      ]
    },

    {
      "question": "question6",
      "options": [
        {
          "answer": "answer6-a",
          "type": { "T": 1 }
        },
        {
          "answer": "answer6-b",
          "type": { "T": -1 }
        }
      ]
    },
    {
      "question": "question7",
      "options": [
        {
          "answer": "answer7-a",
          "type": { "J": -1 }
        },
        {
          "answer": "answer7-b",
          "type": { "J": 1 }
        }
      ]
    },
    {
      "question": "question8",
      "options": [
        {
          "answer": "answer8-a",
          "type": { "E": -1 }
        },
        {
          "answer": "answer8-b",
          "type": { "E": 1 }
        }
      ]
    },
    {
      "question": "question9",
      "options": [
        {
          "answer": "answer9-a",
          "type": { "N": -1 }
        },
        {
          "answer": "answer9-b",
          "type": { "N": 1 }
        }
      ]
    },
    {
      "question": "question10",
      "options": [
        {
          "answer": "answer10-a",
          "type": { "T": 1 }
        },
        {
          "answer": "answer10-b",
          "type": { "T": -1 }
        }
      ]
    },
    {
      "question": "question11",
      "options": [
        {
          "answer": "answer11-a",
          "type": { "E": -1 }
        },
        {
          "answer": "answer11-b",
          "type": { "E": 1 }
        }
      ]
    },
    {
      "question": "question12",
      "options": [
        {
          "answer": "answer12-a",
          "type": { "E": 1 }
        },
        {
          "answer": "answer12-b",
          "type": { "E": -1 }
        }
      ]
    }
  ]
}
